uzum_payments/__init__.py
uzum_payments/client.py
uzum_payments/connection.py
uzum_payments/const.py
uzum_payments/exceptions.py
uzum_payments/receipt_producer/__init__.py
uzum_payments/receipt_producer/client.py
uzum_payments-0.0.6.dist-info/LICENSE
uzum_payments-0.0.6.dist-info/METADATA
uzum_payments-0.0.6.dist-info/WHEEL
uzum_payments-0.0.6.dist-info/top_level.txt
uzum_payments-0.0.6.dist-info/RECORD
