Metadata-Version: 2.1
Name: uzum-payments
Version: 0.0.6
Summary: Uzum Payments API Client
Home-page: https://github.com/homeroff/uzum-payments/
Author: Vsevolod Slivсa
License: MIT
Project-URL: Source Code, https://github.com/homeroff/uzum-payments/
Project-URL: Issue Tracker, https://github.com/homeroff/uzum-payments/issues
Project-URL: Documentation, https://www.inplat-tech.ru/docs/checkout/
Classifier: Development Status :: 3 - Alpha
Classifier: Intended Audience :: Developers
Classifier: License :: OSI Approved :: MIT License
Classifier: Programming Language :: Python :: 3
Classifier: Programming Language :: Python :: 3.6
Classifier: Programming Language :: Python :: 3.7
Classifier: Programming Language :: Python :: 3.8
Classifier: Programming Language :: Python :: 3.9
Classifier: Topic :: Office/Business
Classifier: Topic :: Office/Business :: Financial
Classifier: Topic :: Software Development :: Libraries :: Python Modules
Requires-Python: >=3.6
License-File: LICENSE
Requires-Dist: requests
